Metadata-Version: 2.1
Name: cukuramoto
Version: 1.0.0
Summary: UNKNOWN
Home-page: https://github.com/stdogpkg/cukuramoto
Author: Bruno Messias; Thomas K. Peron
Author-email: messias.physics@gmail.com
License: UNKNOWN
Download-URL: https://github.com/stdogpkg/cukuramoto/archive/v1.0.0.tar.gz
Keywords: cuda,science,complex-networks,graphs,dynamics,tensorflow,kuramoto
Platform: UNKNOWN
Classifier: Development Status :: 4 - Beta
Classifier: License :: OSI Approved :: MIT License
Classifier: Intended Audience :: Science/Research
Classifier: Programming Language :: Python :: 3
Classifier: Topic :: Scientific/Engineering :: Physics
Classifier: Topic :: Scientific/Engineering :: Mathematics
Classifier: Topic :: Scientific/Engineering :: Information Analysis
